{
  "main": {
    "id": "750ca4ddf1736a8b",
    "type": "split",
    "children": [
      {
        "id": "6fa367a37ee60f32",
        "type": "tabs",
        "children": [
          {
            "id": "944552e90874cf9c",
            "type": "leaf",
            "state": {
              "type": "markdown",
              "state": {
                "file": "!komentarz 1.md",
                "mode": "source",
                "source": false
              }
            }
          },
          {
            "id": "b4adae1e03bf6700",
            "type": "leaf",
            "state": {
              "type": "markdown",
              "state": {
                "file": "Zbiór ograniczony w przestrzeni metrycznej.md",
                "mode": "source",
                "source": false
              }
            }
          },
          {
            "id": "47645f94d5c97349",
            "type": "leaf",
            "state": {
              "type": "markdown",
              "state": {
                "file": "Odległość punktu od podzbioru przestrzeni metrycznej.md",
                "mode": "source",
                "source": false
              }
            }
          },
          {
            "id": "ac8f6354a1bd3b57",
            "type": "leaf",
            "state": {
              "type": "markdown",
              "state": {
                "file": "Miara zewnętrzna.md",
                "mode": "source",
                "source": false
              }
            }
          },
          {
            "id": "60b226d7fddbc046",
            "type": "leaf",
            "state": {
              "type": "markdown",
              "state": {
                "file": "Warunek Caratheodory'ego.md",
                "mode": "source",
                "source": false
              }
            }
          }
        ],
        "currentTab": 2
      },
      {
        "id": "9012b5ee195b8ecd",
        "type": "tabs",
        "children": [
          {
            "id": "970eed63b4cc435d",
            "type": "leaf",
            "state": {
              "type": "graph",
              "state": {}
            }
          }
        ]
      }
    ],
    "direction": "vertical"
  },
  "left": {
    "id": "62c70eae72e8d9e1",
    "type": "split",
    "children": [
      {
        "id": "b61dfaac6c46d0ae",
        "type": "tabs",
        "children": [
          {
            "id": "3e256e96eafae490",
            "type": "leaf",
            "state": {
              "type": "file-explorer",
              "state": {
                "sortOrder": "alphabetical"
              }
            }
          },
          {
            "id": "2772c9cd83c32618",
            "type": "leaf",
            "state": {
              "type": "search",
              "state": {
                "query": "",
                "matchingCase": false,
                "explainSearch": true,
                "collapseAll": false,
                "extraContext": true,
                "sortOrder": "alphabetical"
              }
            }
          },
          {
            "id": "4e9ceca707660a03",
            "type": "leaf",
            "state": {
              "type": "bookmarks",
              "state": {}
            }
          }
        ]
      }
    ],
    "direction": "horizontal",
    "width": 305.5
  },
  "right": {
    "id": "81baae406cc65f45",
    "type": "split",
    "children": [
      {
        "id": "1145d2342371283e",
        "type": "tabs",
        "children": [
          {
            "id": "e260e8462c43135f",
            "type": "leaf",
            "state": {
              "type": "backlink",
              "state": {
                "collapseAll": false,
                "extraContext": false,
                "sortOrder": "alphabetical",
                "showSearch": false,
                "searchQuery": "",
                "backlinkCollapsed": false,
                "unlinkedCollapsed": true
              }
            }
          },
          {
            "id": "4d7eda376096720b",
            "type": "leaf",
            "state": {
              "type": "outgoing-link",
              "state": {
                "linksCollapsed": false,
                "unlinkedCollapsed": true
              }
            }
          },
          {
            "id": "fe8dfcbdfb1e6dc3",
            "type": "leaf",
            "state": {
              "type": "tag",
              "state": {
                "sortOrder": "frequency",
                "useHierarchy": true
              }
            }
          },
          {
            "id": "c59ac02a4f1e6b91",
            "type": "leaf",
            "state": {
              "type": "outline",
              "state": {}
            }
          }
        ]
      }
    ],
    "direction": "horizontal",
    "width": 300,
    "collapsed": true
  },
  "left-ribbon": {
    "hiddenItems": {
      "switcher:Otwórz okno szybkiej zmiany pliku": false,
      "graph:Otwórz graf": false,
      "canvas:Stwórz nowe płótno": false,
      "daily-notes:Otwórz dzisiejszą notatkę": false,
      "templates:Wstaw szablon": false,
      "command-palette:Otwórz paletę poleceń": false
    }
  },
  "active": "970eed63b4cc435d",
  "lastOpenFiles": [
    "Odległość punktu od podzbioru przestrzeni metrycznej.md",
    "Zbiór ograniczony w przestrzeni metrycznej.md",
    "Zbiór niespójny.md",
    "Zbiór ograniczony.md",
    "Twierdzenia o szeregach.md",
    "Twierdzenia o zbiorach.md",
    "Twierdzenia o zbiorach domkniętych.md",
    "Twierdzenie Cayleya - Hamiltona.md",
    "Twierdzenie Lagrange'a o warstwach.md",
    "Zbieżność ciągu.md",
    "Miara zewnętrzna.md",
    "Teoria miary.md",
    "Metryka euklidesowa.md",
    "Topologia euklidesowa.md",
    "Topologia.md",
    "Topologia dyskretna i antydyskretna.md",
    "Topologia wykluczonego punktu.md",
    "Topologia przestrzeni metrycznej.md",
    "Topologia wyróżnionego punktu.md",
    "Twierdzenia o zbiorach zwartych.md",
    "Zbiór zwarty.md",
    "Ciąg funkcyjny.md",
    "Ciąg liczbowy.md",
    "Ciało zbiorów.md",
    "Ciąg Cauchy'ego względem metryki.md",
    "Ciąg Cauchy'ego.md",
    "Bez nazwy.canvas"
  ]
}